ladybug_geojson/__init__.py
ladybug_geojson/_geojson_helper.py
ladybug_geojson/_geometry_helper.py
ladybug_geojson/_validator.py
ladybug_geojson/ladybug_feature.py
ladybug_geojson/convert/__init__.py
ladybug_geojson/convert/config.py
ladybug_geojson/convert/from_geometry.py
ladybug_geojson/convert/geojson.py
ladybug_geojson/convert/to_geometry.py
ladybug_geojson/schema/feature.json
ladybug_geojson/schema/featurecollection.json
ladybug_geojson/schema/geometrycollection.json
ladybug_geojson/schema/linestring.json
ladybug_geojson/schema/multilinestring.json
ladybug_geojson/schema/multipoint.json
ladybug_geojson/schema/multipolygon.json
ladybug_geojson/schema/point.json
ladybug_geojson/schema/polygon.json
ladybug_geojson/slippy/__init__.py
ladybug_geojson/slippy/map.py
ladybug_geojson-0.0.3.dist-info/LICENSE
ladybug_geojson-0.0.3.dist-info/METADATA
ladybug_geojson-0.0.3.dist-info/WHEEL
ladybug_geojson-0.0.3.dist-info/top_level.txt
ladybug_geojson-0.0.3.dist-info/RECORD
