Metadata-Version: 2.1
Name: ladybug-geojson
Version: 0.0.3
Summary: Convert geojson types into ladybug geometry types.
Home-page: https://github.com/pollination/ladybug-geojson
Author: Ladybug Tools
Author-email: info@ladybug.tools
License: AGPL-3.0
Classifier: Development Status :: 3 - Alpha
Classifier: Programming Language :: Python :: 3.7
Classifier: Programming Language :: Python :: Implementation :: CPython
Classifier: License :: OSI Approved :: GNU Affero General Public License v3
Classifier: Operating System :: OS Independent
Requires-Python: >=3.7
License-File: LICENSE
Requires-Dist: jsonschema
Requires-Dist: ladybug-core (>=0.39.0)
